hrobot/Listener.py
hrobot/__init__.py
hrobot/hcmd.py
hrobot/hcore.py
hrobot/hkeywords.py
hrobot-0.7.0.dist-info/LICENSE
hrobot-0.7.0.dist-info/METADATA
hrobot-0.7.0.dist-info/WHEEL
hrobot-0.7.0.dist-info/entry_points.txt
hrobot-0.7.0.dist-info/top_level.txt
hrobot-0.7.0.dist-info/RECORD
