Metadata-Version: 2.1
Name: hrobot
Version: 0.7.0
Summary: Hybrid Robot
Home-page: https://github.com/qualitysphere/hrobot
Author: Jing&Will
Author-email: v.stone@163.com
Maintainer: Jing&Will
Maintainer-email: v.stone@163.com
License: Apache
Platform: any
License-File: LICENSE
Requires-Dist: openpyxl (==3.0.9)
Requires-Dist: robotframework (>=4.0.0)
Requires-Dist: allure-robotframework (>=2.9.0)
Requires-Dist: requests (>=2.22.0)
Requires-Dist: selenium (>=3.14.0)
Requires-Dist: paramiko (>=2.7.0)
Requires-Dist: PyYAML (>=5.4.1)
